[{"word":"that","content":[["英式","/ðæt/"],["美式","/ðæt/"]]},{"title":"词义简析","content":[["代词(pron.)","指示远处的事物、人、想法、品质、事件、动作或时间，尤指地理位置远、时间久远或心理距离远的情况。"],["连词(conj.)","引导宾语从句、原因状语从句、目的状语从句、结果状语从句等。"],["副词(adv.)","表示程度，如：极度、非常、到那种程度。"]]},{"title":"场景例句","content":[["指代事物","He went home, and after that I never saw him again.","他回家了，自那以后我再也没有见过他。"],["引导宾语从句","He told me that the book is a good read.","他告诉我那本书很值得一读。"],["表示程度","I did the run last year, and it wasn't that difficult.","我去年跑了这段路，它并没有那么难。"]]},{"title":"相关单词","content":[["this","指代较近的事物或者更加强调的事项","This problem is much easier than that one.","这个问题比那个问题要简单得多。"],["such","表示“如此，这样”的含义，常用来加强语气","She has never seen such a beautiful painting before.","她以前从未见过这样美丽的画。"],["here","与that相对，指代较近的位置或事物","Come here, not there.","来这里，不要去那里。"]]},{"title":"用法小贴士","content":["作为代词时，that用来指代单数或不可数名词，而those用于复数。","作为连词时，that可以引导多种类型的从句，如宾语从句、状语从句等。","作为副词时，that通常用于对比或强调程度，可与so互换。"]},{"title":"今日鼓励","content":"英语中的每一个词都拥有它独特的魅力，掌握它们就像拥有了解世界的密钥。🔑 让我们一步一个脚印，探索语言的奥秘。加油！🚀"}]